_dbdreader.cp311-win_amd64.pyd
dbdreader/__init__.py
dbdreader/dbdreader.py
dbdreader/decompress.py
dbdreader/scripts.py
dbdreader-0.5.5.dist-info/COPYING
dbdreader-0.5.5.dist-info/LICENSE
dbdreader-0.5.5.dist-info/METADATA
dbdreader-0.5.5.dist-info/WHEEL
dbdreader-0.5.5.dist-info/entry_points.txt
dbdreader-0.5.5.dist-info/top_level.txt
dbdreader-0.5.5.dist-info/RECORD
