Metadata-Version: 2.1
Name: dbdreader
Version: 0.5.5
Summary: A python module to access binary data files generated by Teledyne WebbResearch gliders
Home-page: https://dbdreader.readthedocs.io/en/latest/
Author: Lucas Merckelbach
Author-email: lucas.merckelbach@hereon.de
Classifier: Programming Language :: Python :: 3
Classifier: Intended Audience :: Science/Research
Classifier: License :: OSI Approved :: GNU General Public License v3 (GPLv3)
Classifier: Operating System :: POSIX
License-File: LICENSE
License-File: COPYING
Requires-Dist: numpy
Requires-Dist: pytest
Requires-Dist: lz4
